Metadata-Version: 2.1
Name: ToolXmind2Testcase
Version: 0.0.16
Summary: 脑图转换为Excel
Home-page: UNKNOWN
Author: xu.nie
Author-email: xu.nie@shopee.com
License: UNKNOWN
Platform: UNKNOWN
Classifier: Programming Language :: Python :: 3
Classifier: License :: OSI Approved :: MIT License
Classifier: Operating System :: OS Independent
License-File: LICENSE
Requires-Dist: xmindparser
Requires-Dist: pandas
Requires-Dist: click
Requires-Dist: xlsxwriter
